Workbook

Sheet Proyeksi Bulanan
A2: PROYEKSI BULANAN CHURNSENSE - PREDICTIVE CUSTOMER ANALYTICS
A4: Komponen | B4: Unit | C4: Bulan 1 | D4: Bulan 2 | E4: Bulan 3 | F4: Bulan 4 | G4: Bulan 5 | H4: Bulan 6 | I4: Bulan 7 | J4: Bulan 8 | K4: Bulan 9 | L4: Bulan 10 | M4: Bulan 11 | N4: Bulan 12 | O4: Bulan 13 | P4: Bulan 14 | Q4: Bulan 15 | R4: Bulan 16 | S4: Bulan 17 | T4: Bulan 18 | U4: Bulan 19 | V4: Bulan 20 | W4: Bulan 21 | X4: Bulan 22 | Y4: Bulan 23 | Z4: Bulan 24 | AA4: Total
A5: PENDAPATAN
A6: Klien Aktif | B6: klien | C6: 0 | D6: 0 | E6: 0 | F6: 1 | G6: 3 | H6: 5 | I6: 8 | J6: 11 | K6: 15 | L6: 20 | M6: 25 | N6: 30 | O6: 35 | P6: 40 | Q6: 45 | R6: 50 | S6: 55 | T6: 60 | U6: 65 | V6: 70 | W6: 75 | X6: 80 | Y6: 85 | Z6: 90 | AA6: =MAX(C6:Z6)
A7: Harga per Klien | B7: Rp/bulan | C7: 2500000 | D7: 2500000 | E7: 2500000 | F7: 2500000 | G7: 2500000 | H7: 2500000 | I7: 2500000 | J7: 2500000 | K7: 2500000 | L7: 2500000 | M7: 2500000 | N7: 2500000 | O7: 2500000 | P7: 2500000 | Q7: 2500000 | R7: 2500000 | S7: 2500000 | T7: 2500000 | U7: 2500000 | V7: 2500000 | W7: 2500000 | X7: 2500000 | Y7: 2500000 | Z7: 2500000 | AA7: =AVERAGE(C7:Z7)
A8: Total Revenue | B8: Rp/bulan | C8: =C6*C7 | D8: =D6*D7 | E8: =E6*E7 | F8: =F6*F7 | G8: =G6*G7 | H8: =H6*H7 | I8: =I6*I7 | J8: =J6*J7 | ... Z8: =Z6*Z7 | AA8: =SUM(C8:Z8)
A10: HARGA POKOK PENJUALAN (COGS)
A11: Server Hosting & Cloud GPU | B11: Rp/bulan | C11: =IF(C6>0, 500000+C6*50000, 0) | D11: =IF(D6>0, 500000+D6*50000, 0) | E11: =IF(E6>0, 500000+E6*50000, 0) | F11: =IF(F6>0, 500000+F6*50000, 0) | G11: =IF(G6>0, 500000+G6*50000, 0) | H11: =IF(H6>0, 500000+H6*50000, 0) | I11: =IF(I6>0, 500000+I6*50000, 0) | J11: =IF(J6>0, 500000+J6*50000, 0) | ... Z11: =IF(Z6>0, 500000+Z6*50000, 0) | AA11: =SUM(C11:Z11)
A12: Database Cloud (Supabase) | B12: Rp/bulan | C12: =IF(C6>0, 250000+C6*20000, 0) | D12: =IF(D6>0, 250000+D6*20000, 0) | E12: =IF(E6>0, 250000+E6*20000, 0) | F12: =IF(F6>0, 250000+F6*20000, 0) | G12: =IF(G6>0, 250000+G6*20000, 0) | H12: =IF(H6>0, 250000+H6*20000, 0) | I12: =IF(I6>0, 250000+I6*20000, 0) | J12: =IF(J6>0, 250000+J6*20000, 0) | ... Z12: =IF(Z6>0, 250000+Z6*20000, 0) | AA12: =SUM(C12:Z12)
A13: API Services (NLP & Email) | B13: Rp/bulan | C13: =IF(C6>0, 250000+C6*30000, 0) | D13: =IF(D6>0, 250000+D6*30000, 0) | E13: =IF(E6>0, 250000+E6*30000, 0) | F13: =IF(F6>0, 250000+F6*30000, 0) | G13: =IF(G6>0, 250000+G6*30000, 0) | H13: =IF(H6>0, 250000+H6*30000, 0) | I13: =IF(I6>0, 250000+I6*30000, 0) | J13: =IF(J6>0, 250000+J6*30000, 0) | ... Z13: =IF(Z6>0, 250000+Z6*30000, 0) | AA13: =SUM(C13:Z13)
A14: Total COGS | B14: Rp/bulan | C14: =SUM(C11:C13) | D14: =SUM(D11:D13) | E14: =SUM(E11:E13) | F14: =SUM(F11:F13) | G14: =SUM(G11:G13) | H14: =SUM(H11:H13) | I14: =SUM(I11:I13) | J14: =SUM(J11:J13) | ... Z14: =SUM(Z11:Z13) | AA14: =SUM(C14:Z14)
A15: Gross Profit | B15: Rp/bulan | C15: =C8-C14 | D15: =D8-D14 | E15: =E8-E14 | F15: =F8-F14 | G15: =G8-G14 | H15: =H8-H14 | I15: =I8-I14 | J15: =J8-J14 | ... Z15: =Z8-Z14 | AA15: =SUM(C15:Z15)
A16: Gross Profit Margin | B16: % | C16: =IF(C8=0, 0, C15/C8) | D16: =IF(D8=0, 0, D15/D8) | E16: =IF(E8=0, 0, E15/E8) | F16: =IF(F8=0, 0, F15/F8) | G16: =IF(G8=0, 0, G15/G8) | H16: =IF(H8=0, 0, H15/H8) | I16: =IF(I8=0, 0, I15/I8) | J16: =IF(J8=0, 0, J15/J8) | ... AA16: =IF(AA8=0, 0, AA15/AA8)
A18: BIAYA OPERASIONAL (OPEX)
A19: Developer Salary | B19: Rp/bulan | C19: 10000000 | D19: 10000000 | E19: 10000000 | F19: 10000000 | G19: 10000000 | H19: 10000000 | I19: 10000000 | J19: 10000000 | K19: 10000000 | L19: 10000000 | M19: 10000000 | N19: 10000000 | O19: 10000000 | P19: 10000000 | Q19: 10000000 | R19: 10000000 | S19: 10000000 | T19: 10000000 | U19: 10000000 | V19: 10000000 | W19: 10000000 | X19: 10000000 | Y19: 10000000 | Z19: 10000000 | AA19: =SUM(C19:Z19)
A20: Team Leader / PM Salary | B20: Rp/bulan | C20: 13000000 | D20: 13000000 | E20: 13000000 | F20: 13000000 | G20: 13000000 | H20: 13000000 | I20: 13000000 | J20: 13000000 | K20: 13000000 | L20: 13000000 | M20: 13000000 | N20: 13000000 | O20: 13000000 | P20: 13000000 | Q20: 13000000 | R20: 13000000 | S20: 13000000 | T20: 13000000 | U20: 13000000 | V20: 13000000 | W20: 13000000 | X20: 13000000 | Y20: 13000000 | Z20: 13000000 | AA20: =SUM(C20:Z20)
A21: Marketing & Sales Team | B21: Rp/bulan | C21: 10000000 | D21: 10000000 | E21: 10000000 | F21: 10000000 | G21: 10000000 | H21: 10000000 | I21: 10000000 | J21: 10000000 | K21: 10000000 | L21: 10000000 | M21: 10000000 | N21: 10000000 | O21: 10000000 | P21: 10000000 | Q21: 10000000 | R21: 10000000 | S21: 10000000 | T21: 10000000 | U21: 10000000 | V21: 10000000 | W21: 10000000 | X21: 10000000 | Y21: 10000000 | Z21: 10000000 | AA21: =SUM(C21:Z21)
A22: Sewa Gedung & Utilitas | B22: Rp/bulan | C22: 2500000 | D22: 2500000 | E22: 2500000 | F22: 2500000 | G22: 2500000 | H22: 2500000 | I22: 2500000 | J22: 2500000 | K22: 2500000 | L22: 2500000 | M22: 2500000 | N22: 2500000 | O22: 2500000 | P22: 2500000 | Q22: 2500000 | R22: 2500000 | S22: 2500000 | T22: 2500000 | U22: 2500000 | V22: 2500000 | W22: 2500000 | X22: 2500000 | Y22: 2500000 | Z22: 2500000 | AA22: =SUM(C22:Z22)
A23: Internet & Listrik | B23: Rp/bulan | C23: 1000000 | D23: 1000000 | E23: 1000000 | F23: 1000000 | G23: 1000000 | H23: 1000000 | I23: 1000000 | J23: 1000000 | K23: 1000000 | L23: 1000000 | M23: 1000000 | N23: 1000000 | O23: 1000000 | P23: 1000000 | Q23: 1000000 | R23: 1000000 | S23: 1000000 | T23: 1000000 | U23: 1000000 | V23: 1000000 | W23: 1000000 | X23: 1000000 | Y23: 1000000 | Z23: 1000000 | AA23: =SUM(C23:Z23)
A24: Total OpEx | B24: Rp/bulan | C24: =SUM(C19:C23) | D24: =SUM(D19:D23) | E24: =SUM(E19:E23) | F24: =SUM(F19:F23) | G24: =SUM(G19:G23) | H24: =SUM(H19:H23) | I24: =SUM(I19:I23) | J24: =SUM(J19:J23) | ... Z24: =SUM(Z19:Z23) | AA24: =SUM(C24:Z24)
A26: KEUNTUNGAN BERSIH
A27: Net Profit (EBT) | B27: Rp/bulan | C27: =C15-C24 | D27: =D15-D24 | E27: =E15-E24 | F27: =F15-F24 | G27: =G15-G24 | H27: =H15-H24 | I27: =I15-I24 | J27: =J15-J24 | ... Z27: =Z15-Z24 | AA27: =SUM(C27:Z27)
A28: Pajak Penghasilan (11%) | B28: Rp/bulan | C28: =IF(C27>0, C27*0.11, 0) | D28: =IF(D27>0, D27*0.11, 0) | E28: =IF(E27>0, E27*0.11, 0) | F28: =IF(F27>0, F27*0.11, 0) | G28: =IF(G27>0, G27*0.11, 0) | H28: =IF(H27>0, H27*0.11, 0) | I28: =IF(I27>0, I27*0.11, 0) | J28: =IF(J27>0, J27*0.11, 0) | ... Z28: =IF(Z27>0, Z27*0.11, 0) | AA28: =SUM(C28:Z28)
A29: Net Profit After Tax | B29: Rp/bulan | C29: =C27-C28 | D29: =D27-D28 | E29: =E27-E28 | F29: =F27-F28 | G29: =G27-G28 | H29: =H27-H28 | I29: =I27-I28 | J29: =J27-J28 | ... Z29: =Z27-Z28 | AA29: =SUM(C29:Z29)
A30: Cumulative Cash Flow | B30: Rp | C30: =-'Analisis Kelayakan'!B4+C29 | D30: =C30+D29 | E30: =D30+E29 | F30: =E30+F29 | G30: =F30+G29 | H30: =G30+H29 | I30: =H30+I29 | J30: =I30+J29 | K30: =J30+K29 | ... Z30: =Y30+Z29 | AA30: -

Sheet Analisis Kelayakan
A2: ANALISIS KELAYAKAN FINANSIAL CHURNSENSE
A4: Parameter | B4: Nilai | C4: Keterangan | G4: Periode | H4: Cash Flow
A5: Investasi Awal (Modal) | B5: 600000000 | C5: Mencakup capex & working capital untuk operasional 11 bulan pertama | G5: Bulan 0 | H5: =-B5
A6: Discount Rate (Annual) | B6: 0.12 | C6: Tingkat suku bunga acuan / biaya modal tahunan | G6: Bulan 1 | H6: ='Proyeksi Bulanan'!C29
G7: Bulan 2 | H7: ='Proyeksi Bulanan'!D29
G8: Bulan 3 | H8: ='Proyeksi Bulanan'!E29
A9: NET PRESENT VALUE (NPV) | D9: INTERNAL RATE OF RETURN (IRR) | G9: Bulan 4 | H9: ='Proyeksi Bulanan'!F29
A10: =NPV(B6/12, H6:H29)+H5 | D10: =IRR(H5:H29)*12 | G10: Bulan 5 | H10: ='Proyeksi Bulanan'!G29
G11: Bulan 6 | H11: ='Proyeksi Bulanan'!H29
G12: Bulan 7 | H12: ='Proyeksi Bulanan'!I29
A13: PAYBACK PERIOD (PP) | D13: PROFITABILITY INDEX (PI) | G13: Bulan 8 | H13: ='Proyeksi Bulanan'!J29
A14: 20 Bulan | D14: =(A10+B5)/B5 | G14: Bulan 9 | H14: ='Proyeksi Bulanan'!K29
G15: Bulan 10 | H15: ='Proyeksi Bulanan'!L29
G16: Bulan 11 | H16: ='Proyeksi Bulanan'!M29
A17: Kesimpulan Kelayakan Finansial: | G17: Bulan 12 | H17: ='Proyeksi Bulanan'!N29
A18: 1. Net Present Value (NPV) > 0 (Positif): Investasi ini layak secara finansial karena nilai sekarang dari arus kas masa depan lebih besar dari modal awal. | G18: Bulan 13 | H18: ='Proyeksi Bulanan'!O29
A19: 2. IRR > Discount Rate (12%): Tingkat pengembalian internal proyek jauh melampaui tingkat suku bunga acuan bank, menandakan investasi sangat menguntungkan. | G19: Bulan 14 | H19: ='Proyeksi Bulanan'!P29
A20: 3. Payback Period (20 Bulan): Seluruh modal investasi awal sebesar Rp 600.000.000 akan sepenuhnya kembali pada bulan ke-20. | G20: Bulan 15 | H20: ='Proyeksi Bulanan'!Q29
A21: 4. Profitability Index (PI) > 1.0: Setiap Rp 1 yang diinvestasikan menghasilkan nilai lebih dari Rp 1, yang menunjukkan efisiensi investasi yang sangat baik. | G21: Bulan 16 | H21: ='Proyeksi Bulanan'!R29
G22: Bulan 17 | H22: ='Proyeksi Bulanan'!S29
G23: Bulan 18 | H23: ='Proyeksi Bulanan'!T29
G24: Bulan 19 | H24: ='Proyeksi Bulanan'!U29
G25: Bulan 20 | H25: ='Proyeksi Bulanan'!V29
G26: Bulan 21 | H26: ='Proyeksi Bulanan'!W29
G27: Bulan 22 | H27: ='Proyeksi Bulanan'!X29
G28: Bulan 23 | H28: ='Proyeksi Bulanan'!Y29
G29: Bulan 24 | H29: ='Proyeksi Bulanan'!Z29
